kanbanpy/__init__.py
kanbanpy/__main__.py
kanbanpy/cli.py
kanbanpy/models.py
kanbanpy/storage.py
kanbanpy-2.2.0.dist-info/LICENSE
kanbanpy-2.2.0.dist-info/METADATA
kanbanpy-2.2.0.dist-info/WHEEL
kanbanpy-2.2.0.dist-info/entry_points.txt
kanbanpy-2.2.0.dist-info/RECORD
