Metadata-Version: 2.3
Name: kanbanpy
Version: 2.2.0
Summary: A console-based Kanban task manager created in Python.
License: MIT License
Keywords: kanban,project,management
Author: Óscar Miranda
Author-email: oscarmiranda3615@gmail.com
Requires-Python: >=3.9
Classifier: Environment :: Console
Classifier: Intended Audience :: Developers
Classifier: Intended Audience :: Information Technology
Classifier: License :: OSI Approved :: MIT License
Classifier: Operating System :: OS Independent
Classifier: Programming Language :: Python :: 3
Classifier: Topic :: Software Development
Classifier: Topic :: Utilities
Requires-Dist: platformdirs (>=4.3.7,<5.0.0)
Requires-Dist: rich (>=14.0.0,<15.0.0)
Project-URL: Homepage, https://github.com/OscarM3615/kanbanpy
Project-URL: Repository, https://github.com/OscarM3615/kanbanpy
